transformer_checker/__init__.py
transformer_checker/dataset/__init__.py
transformer_checker/dataset/dyck_language_dataset.py
transformer_checker/dyck_k_generator/__init__.py
transformer_checker/dyck_k_generator/checker.py
transformer_checker/dyck_k_generator/constants.py
transformer_checker/dyck_k_generator/generator.py
transformer_checker/transformer/__init__.py
transformer_checker/transformer/hooked_transformer.py
transformer_checker/transformer_viz/__init__.py
transformer_checker/transformer_viz/visualizer.py
transformer_checker-0.1.8.dist-info/METADATA
transformer_checker-0.1.8.dist-info/WHEEL
transformer_checker-0.1.8.dist-info/entry_points.txt
transformer_checker-0.1.8.dist-info/RECORD
